heps_ds_utils/__init__.py
heps_ds_utils/bigquery_operations.py
heps_ds_utils/bucket_operations.py
heps_ds_utils/elastic_operations.py
heps_ds_utils/hive_operations.py
heps_ds_utils/http_request_operations.py
heps_ds_utils/kafka_operations.py
heps_ds_utils/logging_operations.py
heps_ds_utils/mongo_operations.py
heps_ds_utils/read_from_bq_file.py
heps_ds_utils/slack_operations.py
heps_ds_utils-0.5.0.dist-info/LICENSE
heps_ds_utils-0.5.0.dist-info/METADATA
heps_ds_utils-0.5.0.dist-info/WHEEL
heps_ds_utils-0.5.0.dist-info/RECORD
