Metadata-Version: 2.1
Name: heps_ds_utils
Version: 0.5.0
Summary: A Module to enable Hepsiburada Data Science Team to utilize different tools.
License: MIT
Author: FarukBuldur
Author-email: faruk.buldur@hepsiburada.com
Maintainer: FıratÖncü
Maintainer-email: firat.oncu@hepsiburada.com
Requires-Python: >=3.8,<3.11
Classifier: License :: OSI Approved :: MIT License
Classifier: Operating System :: MacOS
Classifier: Operating System :: POSIX :: Linux
Classifier: Programming Language :: Python :: 3
Classifier: Programming Language :: Python :: 3.8
Classifier: Programming Language :: Python :: 3.9
Classifier: Programming Language :: Python :: 3.10
Provides-Extra: hive
Requires-Dist: PyHive (>=0.6.5,<0.7.0) ; extra == "hive"
Requires-Dist: colorama (>=0.4.4,<0.5.0)
Requires-Dist: elasticsearch (==7.17.7)
Requires-Dist: google-cloud-bigquery[bqstorage,pandas] (>=3.0.1,<4.0.0)
Requires-Dist: google-cloud-logging (>=3.0.0,<4.0.0)
Requires-Dist: google-cloud-storage (>=2.5.0,<3.0.0)
Requires-Dist: pandas (>=1.4.1,<=2.0.3)
Requires-Dist: paramiko (>=2.10.3,<3.0.0)
Requires-Dist: pymongo (>=4.3.2,<5.0.0)
Requires-Dist: sasl (>=0.3.1,<0.4.0) ; (sys_platform == "linux" or sys_platform == "darwin") and (extra == "hive")
Requires-Dist: scp (>=0.14.4,<0.15.0) ; extra == "hive"
Requires-Dist: thrift (>=0.15.0,<0.16.0) ; extra == "hive"
Requires-Dist: thrift-sasl (>=0.4.3,<0.5.0) ; extra == "hive"
Requires-Dist: tqdm (>=4.65.0,<5.0.0)
